migration_runner/__init__.py
migration_runner/cli.py
migration_runner/controller.py
migration_runner/database_tools.py
migration_runner/helpers.py
migration_runner-0.3.4.dist-info/LICENSE
migration_runner-0.3.4.dist-info/METADATA
migration_runner-0.3.4.dist-info/WHEEL
migration_runner-0.3.4.dist-info/entry_points.txt
migration_runner-0.3.4.dist-info/top_level.txt
migration_runner-0.3.4.dist-info/RECORD
