Metadata-Version: 2.1
Name: migration-runner
Version: 0.3.4
Summary: Run MySQL migration scripts sequentially from a specified directory, keeping track of current version in the database.
Home-page: https://github.com/beveradb/migration_runner
Author: Andrew Beveridge
Author-email: andrew@beveridge.uk
License: MIT license
Keywords: migration_runner
Platform: UNKNOWN
Classifier: Development Status :: 3 - Alpha
Classifier: Intended Audience :: Developers
Classifier: License :: OSI Approved :: MIT License
Classifier: Natural Language :: English
Classifier: Programming Language :: Python :: 2
Classifier: Programming Language :: Python :: 2.7
Classifier: Programming Language :: Python :: 3
Classifier: Programming Language :: Python :: 3.5
Classifier: Programming Language :: Python :: 3.6
Classifier: Programming Language :: Python :: 3.7
Requires-Dist: Click (>=7.0)
Requires-Dist: click-log (>=0.3.2)
